telegrambot/__init__.py
telegrambot/bot.py
telegrambot/command.py
telegrambot/context.py
telegrambot_py-0.1.0.dist-info/LICENSE
telegrambot_py-0.1.0.dist-info/METADATA
telegrambot_py-0.1.0.dist-info/WHEEL
telegrambot_py-0.1.0.dist-info/top_level.txt
telegrambot_py-0.1.0.dist-info/RECORD
