Metadata-Version: 2.1
Name: telegrambot-py
Version: 0.1.0
Summary: Make your own telegram bot easily
Home-page: https://github.com/hellodhlyn/telegrambot-py
Author: Do Hoerin
Author-email: lyn@lynlab.co.kr
License: MIT
Platform: UNKNOWN
Classifier: Programming Language :: Python :: 3.5
Classifier: Programming Language :: Python :: 3.6
Classifier: Programming Language :: Python :: 3.7
Requires-Python: >=3.5
